{
  "scraped_at": "2026-05-14T08:26:54",
  "queries": [
    {
      "query": "인수 합병 경영권취득 주식확보 금융적합작관계 전략적제휴 지분매각",
      "or_query": "인수 | 합병 | 경영권취득 | 주식확보 | 금융적합작관계 | 전략적제휴 | 지분매각",
      "total": 10,
      "articles": [
        {
          "title": "SK텔레콤, 브로드밴드 완전자회사 '초읽기'…<mark>합병</mark> 가능성은",
          "link": "https://www.topdaily.kr/articles/110088",
          "published_at": "8시간 전"
        },
        {
          "title": "몸값 8조원 ‘배민’ <mark>매각</mark> 착수…DH, 네이버·우버·알리바바 등에 <mark>인수</mark>...",
          "link": "https://sateconomy.co.kr/news/view/1065576256877280",
          "published_at": "6시간 전"
        },
        {
          "title": "카카오모빌리티, '<mark>매각</mark>설' 선긋고 투자전략 손질…미국 상장카드 부상",
          "link": "http://www.seouleconews.com/news/articleView.html?idxno=91228",
          "published_at": "5시간 전"
        },
        {
          "title": "[더벨]지씨지놈, 초기 FI 엑시트 오버행 해소 '이젠 밸류업 시간'",
          "link": "https://www.thebell.co.kr/free/content/ArticleView.asp?key=202605111425084520107023",
          "published_at": "1일 전"
        },
        {
          "title": "SKC, 비주력 사업 추가 <mark>매각</mark> 뒤 계열사와 <mark>합병</mark> 가능성 부상… 잠재 매물...",
          "link": "https://biz.chosun.com/stock/market_trend/2026/05/14/2K3ZEJ2OHBBS3J4CLCVMBARHVU/?utm_source=naver&utm_medium=original&utm_campaign=biz",
          "published_at": "9시간 전"
        },
        {
          "title": "배민 새 주인 찾나… 딜리버리히어로, 우아한형제들 <mark>매각</mark> 추진",
          "link": "https://www.koreaittimes.com/news/articleView.html?idxno=153729",
          "published_at": "8시간 전"
        },
        {
          "title": "[컨콜] 삼성생명 &quot;삼성전자 특별배당도 재원에 포함&quot;…주주환원 구체안...",
          "link": "https://www.newspim.com/news/view/20260514001009",
          "published_at": "2시간 전"
        },
        {
          "title": "비이랩, 웰데이타시스템 <mark>인수</mark>…AI·클라우드 공략 강화",
          "link": "https://www.sedaily.com/article/20043838?ref=naver",
          "published_at": "9시간 전"
        },
        {
          "title": "한샘, 결국 넥서스도 합친다…구조조정 가속화",
          "link": "https://news.bizwatch.co.kr/article/consumer/2026/05/13/0031",
          "published_at": "10시간 전"
        },
        {
          "title": "매뉴라이프 1분기 순이익 급증…자산운용 44억달러 순유출은 부담",
          "link": "https://www.tokenpost.kr/news/market/359417",
          "published_at": "10시간 전"
        }
      ]
    },
    {
      "query": "IPO",
      "or_query": "IPO",
      "total": 10,
      "articles": [
        {
          "title": "'엔비디아 경쟁사' 세레브라스 시총 84조원에 상장",
          "link": "https://www.yna.co.kr/view/AKR20260514088300009?input=1195m",
          "published_at": "5시간 전"
        },
        {
          "title": "&quot;개발 3일→1시간&quot; 마법 부린 메가존클라우드…&quot;AI 지휘자로 <mark>IPO</mark> 속도 낸...",
          "link": "https://www.newsis.com/view/NISX20260514_0003629364",
          "published_at": "3시간 전"
        },
        {
          "title": "6500억 VC와 손잡은 하나증권...스타트업 발굴을 <mark>IPO</mark>·M&amp;A로 잇는다",
          "link": "https://www.insight.co.kr/news/554126",
          "published_at": "1시간 전"
        },
        {
          "title": "사라진 스톡옵션 취소…컬리, 폭풍 성장에 직원들도 <mark>IPO</mark> 기대",
          "link": "https://www.news1.kr/industry/distribution/6164482",
          "published_at": "10시간 전"
        },
        {
          "title": "[컬리 <mark>IPO</mark> 재도전]② 네이버 등장, 2.8조 밸류 방어 나섰다",
          "link": "https://www.bloter.net/news/articleView.html?idxno=662136",
          "published_at": "1일 전"
        },
        {
          "title": "[내일의 KIW]몸값 1조 딥엑스부터 지드래곤 소속사, <mark>IPO</mark> 무대 선다",
          "link": "https://www.hankyung.com/article/202605146970i",
          "published_at": "43분 전"
        },
        {
          "title": "[피스피스스튜디오 <mark>IPO</mark>] '김고은 꽃무늬옷' 이미 해외에서도 시들",
          "link": "https://dealsite.co.kr/articles/161696",
          "published_at": "7시간 전"
        },
        {
          "title": "[카드] 마키나락스, 우리사주 100% 완판…<mark>IPO</mark> '흥행 4관왕' 달성",
          "link": "http://www.newsprime.co.kr/news/article.html?no=733408",
          "published_at": "8시간 전"
        },
        {
          "title": "<mark>IPO</mark> ‘따따블’ 행진에도…중복상장 금지에 ‘발목’",
          "link": "https://www.dailian.co.kr/news/view/1643848/?sc=Naver",
          "published_at": "10시간 전"
        },
        {
          "title": "<mark>IPO</mark> 앞둔 앤스로픽, 오픈AI 추월 눈앞",
          "link": "https://www.naeil.com/news/read/588640?ref=naver",
          "published_at": "4시간 전"
        }
      ]
    },
    {
      "query": "PE PEF 사모펀드 펀드조성 지분매각 VIG 스틱인베스트먼트 한앤코 MBK파트너스 어피너티",
      "or_query": "PE | PEF | 사모펀드 | 펀드조성 | 지분매각 | VIG | 스틱인베스트먼트 | 한앤코 | MBK파트너스 | 어피너티",
      "total": 10,
      "articles": [
        {
          "title": "IMM <mark>PE</mark> '4조원대 에어퍼스트' 컨티뉴에이션 <mark>펀드 조성</mark> 시동…UBS 자문",
          "link": "https://www.etoday.co.kr/news/view/2584546",
          "published_at": "1시간 전"
        },
        {
          "title": "SK증권, SKS <mark>PE</mark> 앞세워 친환경·반도체 투자 강화…‘산업’ 존재감 확대",
          "link": "http://www.thevaluenews.co.kr/news/view.php?idx=198683",
          "published_at": "10시간 전"
        },
        {
          "title": "배민 새 주인 찾나… 딜리버리히어로, 우아한형제들 <mark>매각</mark> 추진",
          "link": "https://www.koreaittimes.com/news/articleView.html?idxno=153729",
          "published_at": "8시간 전"
        },
        {
          "title": "골프존카운티 예비입찰 29일 마감…원매자 ‘북적’ 흥행 청신호 [시그...",
          "link": "https://www.sedaily.com/article/20043602?ref=naver",
          "published_at": "11시간 전"
        },
        {
          "title": "[더벨][<mark>VIG</mark><mark>파트너스</mark> 3.0 시작] 3세대 핵심 파트너, 정연박·한영기·한영...",
          "link": "https://www.thebell.co.kr/free/content/ArticleView.asp?key=202605121459307840102560",
          "published_at": "9시간 전"
        },
        {
          "title": "[김광현의 기업살롱] <mark>사모펀드</mark>의 락앤락 작년 투자회수 무려 2648억원",
          "link": "http://www.nongaek.com/news/articleView.html?idxno=95382",
          "published_at": "15분 전"
        },
        {
          "title": "[HMM50년 돌아보기-42] 부산신항터미널 <mark>지분 매각</mark>",
          "link": "http://www.thebigdata.co.kr/view.php?ud=202605140858399771570d99e4c8_23",
          "published_at": "8시간 전"
        },
        {
          "title": "'7대 1의 혈투' 7조원대 투자 마중물 확보戰 스타트[국민성장<mark>펀드</mark> 운용...",
          "link": "https://www.etoday.co.kr/news/view/2583495",
          "published_at": "1일 전"
        },
        {
          "title": "공무원연금공단, '밀크티·치즈 열풍'수혜 UCK 투자해 높은 수익",
          "link": "https://www.hankyung.com/article/202605134400r",
          "published_at": "8시간 전"
        },
        {
          "title": "(<mark>사모펀드</mark>발 '자본의 역습')①프랜차이즈 새 주인은 '투자자본'…수익성...",
          "link": "http://www.newstomato.com/ReadNews.aspx?no=1300669&inflow=N",
          "published_at": "1일 전"
        }
      ]
    },
    {
      "query": "앵커에퀴티파트너스 H&Q아시아퍼시픽코리아 칼라일 KKR 블랙스톤",
      "or_query": "앵커에퀴티파트너스 | H&Q아시아퍼시픽코리아 | 칼라일 | KKR | 블랙스톤",
      "total": 10,
      "articles": [
        {
          "title": "현직이 푸는 사모펀드 환매중단 사태 2: 은행을 조졌더니 괴물이 나왔네...",
          "link": "http://www.ddanzi.com/881067657",
          "published_at": "1일 전"
        },
        {
          "title": "라인게임즈 투자 갈등 격화…'사업권 보장계약 위반' 분쟁 속 저가 유상...",
          "link": "https://www.nbntv.kr/news/articleView.html?idxno=340100",
          "published_at": "1시간 전"
        },
        {
          "title": "구글도 FDE 수백명 채용...AI 경쟁, '모델'에서 '현장 도입'으로",
          "link": "https://www.aitimes.com/news/articleView.html?idxno=210447",
          "published_at": "22시간 전"
        },
        {
          "title": "SK네트웍스, 자산 효율화에 1분기 영업익 전년比 102% 증가 … AI 성장 전...",
          "link": "https://biz.newdaily.co.kr/site/data/html/2026/05/13/2026051300315.html",
          "published_at": "22시간 전"
        },
        {
          "title": "AI發 감원 러시에도 AI 현장 엔지니어 전성시대...구글도 수백여명 채용",
          "link": "https://www.digitaltoday.co.kr/news/articleView.html?idxno=665501",
          "published_at": "1일 전"
        },
        {
          "title": "[구경제 부활] ①1979·2020·2026, 병목이 강제하는 자본 재편",
          "link": "https://www.newspim.com/news/view/20260513000558",
          "published_at": "1일 전"
        },
        {
          "title": "<mark>블랙스톤</mark> BXDC, IPO 주당 20달러 확정…데이터센터 투자 본격화",
          "link": "https://www.tokenpost.kr/news/market/359572",
          "published_at": "3시간 전"
        },
        {
          "title": "<mark>블랙스톤</mark>, AI 데이터센터 투자 리츠 상장…17억5000만달러 조달",
          "link": "https://www.g-enews.com/view.php?ud=2026051408572396609a1f309431_1",
          "published_at": "8시간 전"
        },
        {
          "title": "[리걸타임즈 특집=Rising Stars 2026] 이희웅 변호사",
          "link": "http://www.legaltimes.co.kr/news/articleView.html?idxno=93768",
          "published_at": "59분 전"
        },
        {
          "title": "트럼프 동행한 ‘1조 달러’ 클럽…中서 ‘빅딜’ 따낼까",
          "link": "https://www.kmib.co.kr/article/view.asp?arcid=0029821161&code=61131111&cp=nv",
          "published_at": "1시간 전"
        }
      ]
    },
    {
      "query": "국민연금 공무원연금 사학연금 우체국보험기금 군인공제회 교직원공제회 과학기술인공제회 행정공제회",
      "or_query": "국민연금 | 공무원연금 | 사학연금 | 우체국보험기금 | 군인공제회 | 교직원공제회 | 과학기술인공제회 | 행정공제회",
      "total": 10,
      "articles": [
        {
          "title": "우리은행, 4대 공적<mark>연금</mark> 계좌변경 비대면 확대",
          "link": "http://www.paxetv.com/news/articleView.html?idxno=271987",
          "published_at": "19시간 전"
        },
        {
          "title": "국내주식 비중 4배 늘린 건근공…신익철 CIO의 승부수 통했다",
          "link": "http://www.edaily.co.kr/news/newspath.asp?newsid=05313606645448592",
          "published_at": "1일 전"
        },
        {
          "title": "<mark>연금</mark>·여행·콘텐츠까지…은행권, 생활밀착형 금융 경쟁 확대",
          "link": "http://www.dailypop.kr/news/articleView.html?idxno=98804",
          "published_at": "8시간 전"
        },
        {
          "title": "‘역대급 국장 수익률’ <mark>국민연금</mark>, 주식운용실장에 김수연 팀장 승진 임...",
          "link": "https://www.mk.co.kr/article/12047706",
          "published_at": "1시간 전"
        },
        {
          "title": "재정적자 6년來 최소...<mark>국민연금</mark>수익·주식거래세수 등 증가",
          "link": "http://www.metroseoul.co.kr/article/20260514500231",
          "published_at": "1시간 전"
        },
        {
          "title": "&quot;집도 차도 아내 명의인데&quot; 30년 참다 황혼이혼...재산분할 쟁점은",
          "link": "https://www.mt.co.kr/society/2026/05/14/2026051414130125355",
          "published_at": "2시간 전"
        },
        {
          "title": "[은행 이모저모] 하나은행·우리은행·농협은행 등",
          "link": "http://www.bizwnews.com/news/articleView.html?idxno=136481",
          "published_at": "6시간 전"
        },
        {
          "title": "[#금융톡톡] 우리은행 <mark>연금</mark>계좌 확대·하나銀 GLN 중국 QR결제 강화·농...",
          "link": "https://www.newsworks.co.kr/news/articleView.html?idxno=840620",
          "published_at": "1일 전"
        },
        {
          "title": "[금융단신] <mark>국민</mark>은행·하나은행·우리은행·기업은행",
          "link": "https://daily.hankooki.com/news/articleView.html?idxno=1366763",
          "published_at": "1일 전"
        },
        {
          "title": "어린이집안전<mark>공제회</mark> &quot;보육<mark>교직원</mark> 권익보호 특약 가입률 80%↑&quot;",
          "link": "http://www.babytimes.co.kr/news/articleView.html?idxno=72941",
          "published_at": "5시간 전"
        }
      ]
    },
    {
      "query": "경찰공제회 건설근로자공제회 한국지방재정공제회 대한소방공제회 새마을금고중앙회 농협중앙회",
      "or_query": "경찰공제회 | 건설근로자공제회 | 한국지방재정공제회 | 대한소방공제회 | 새마을금고중앙회 | 농협중앙회",
      "total": 10,
      "articles": [
        {
          "title": "국내주식 비중 4배 늘린 건근공…신익철 CIO의 승부수 통했다",
          "link": "http://www.edaily.co.kr/news/newspath.asp?newsid=05313606645448592",
          "published_at": "1일 전"
        },
        {
          "title": "<mark>한국</mark>행정학회 'AI행정 패러다임 혁신사례' 세미나",
          "link": "https://www.newsis.com/view/NISX20260514_0003630009",
          "published_at": "30분 전"
        },
        {
          "title": "<mark>한국지방재정공제회</mark>, 17개 광역 지자체 도심 침수 예방 지원",
          "link": "https://www.cnbnews.com/news/articleView.html?idxno=1001675",
          "published_at": "19시간 전"
        },
        {
          "title": "<mark>농협중앙회</mark>, &quot;신뢰받는 <mark>농협</mark> 구현&quot; 다짐",
          "link": "http://www.bokuennews.com/news/article.html?no=278172",
          "published_at": "29분 전"
        },
        {
          "title": "<mark>경찰</mark>, <mark>농협중앙회</mark> 준법지원부 압수수색…임직원 변호사비 대납 의혹",
          "link": "https://www.financialpost.co.kr/news/articleView.html?idxno=259156",
          "published_at": "21분 전"
        },
        {
          "title": "하동군, 군민안전보험 보장 강화..“재난·사고 군민 피해 최소화”",
          "link": "https://www.dnews.co.kr/uhtml/view.jsp?idxno=202605132005217350652",
          "published_at": "9시간 전"
        },
        {
          "title": "전통시장에서 안전사고 당해도..&quot;배상은 국가에서?&quot;",
          "link": "https://mbcgn.kr/01_new/new01_view.asp?idx=408072",
          "published_at": "19시간 전"
        },
        {
          "title": "하동군, 군민안전보험 강화... 재난 사망·신규 위험 보장",
          "link": "http://www.gnmaeil.com/news/articleView.html?idxno=586548",
          "published_at": "19시간 전"
        },
        {
          "title": "[단독] 실손24 밖 공제보험 52만건…<mark>새마을</mark>·교직원 '사각지대'",
          "link": "https://www.kbanker.co.kr/news/articleView.html?idxno=224925",
          "published_at": "3시간 전"
        },
        {
          "title": "인천시회, <mark>건설</mark>현장 노무역량 도약전략·분쟁대응 강습회 개최",
          "link": "https://www.koscaj.com/news/articleView.html?idxno=324117",
          "published_at": "1시간 전"
        }
      ]
    },
    {
      "query": "신협중앙회 수협중앙회 중소기업중앙회 노란우산 산업은행 수출입은행 삼성생명 우정사업본부",
      "or_query": "신협중앙회 | 수협중앙회 | 중소기업중앙회 | 노란우산 | 산업은행 | 수출입은행 | 삼성생명 | 우정사업본부",
      "total": 10,
      "articles": [
        {
          "title": "폐업부터 재취업까지…중기<mark>중앙회</mark>, 소상공인 지원 확대",
          "link": "https://www.dailian.co.kr/news/view/1644326/?sc=Naver",
          "published_at": "2시간 전"
        },
        {
          "title": "중기<mark>중앙회</mark>, 소상공인 재도약·협동조합 글로벌 진출 설명회 개최",
          "link": "http://www.metroseoul.co.kr/article/20260514500242",
          "published_at": "1시간 전"
        },
        {
          "title": "[단독] 실손24 밖 공제보험 52만건…새마을·교직원 '사각지대'",
          "link": "https://www.kbanker.co.kr/news/articleView.html?idxno=224925",
          "published_at": "3시간 전"
        },
        {
          "title": "[자산운용 新경영전략②] 이준용·최창훈 미래에셋운용 대표, AUM 600조 ‘...",
          "link": "https://www.mydaily.co.kr/page/view/2026051217213931976",
          "published_at": "1일 전"
        },
        {
          "title": "중기<mark>중앙회</mark> 서울<mark>본부</mark>, 수유전통시장서 '시장활력 제고 캠페인' 전개",
          "link": "https://www.pinpointnews.co.kr/news/articleView.html?idxno=452670",
          "published_at": "4시간 전"
        },
        {
          "title": "인천 지역경제의 뿌리, 소상공인을 지켜야 한다",
          "link": "https://www.kihoilbo.co.kr/news/articleView.html?idxno=3022784",
          "published_at": "2시간 전"
        },
        {
          "title": "<mark>노란우산</mark> 이어 공제기금도 DX…중기<mark>중앙회</mark> 'KBIZ 통합공제' 추진",
          "link": "https://www.sidae.com/article/2026051309462868443",
          "published_at": "1일 전"
        },
        {
          "title": "중기<mark>중앙회</mark> 인천, <mark>중소기업</mark> CEO 대상 AI 역량강화 교육 개최",
          "link": "https://www.livesnews.com/news/article.html?no=61447",
          "published_at": "22시간 전"
        },
        {
          "title": "중기<mark>중앙회</mark>-저고위, 저출생 대응…&quot;실효성 있는 지원책 강화&quot;",
          "link": "https://www.news1.kr/industry/general-industry/6164828",
          "published_at": "1일 전"
        },
        {
          "title": "소상공인 직접 찾아가는 '<mark>노란우산</mark> 방문상담'",
          "link": "https://www.ksilbo.co.kr/news/articleView.html?idxno=1056587",
          "published_at": "1일 전"
        }
      ]
    },
    {
      "query": "한국증권금융 출자",
      "or_query": "한국증권금융 | 출자",
      "total": 10,
      "articles": [
        {
          "title": "한투 1분기 영업익 1조원 육박…“위탁·운용·WM·IB '육각형 수익구조...",
          "link": "https://www.hankyung.com/article/202605146375i",
          "published_at": "10분 전"
        },
        {
          "title": "한투<mark>증권</mark>, 1분기 영업익 1조원 육박…전년 대비 85% 증가(종합)",
          "link": "https://www.yna.co.kr/view/AKR20260514149351527?input=1195m",
          "published_at": "25분 전"
        },
        {
          "title": "<mark>한국</mark>투자<mark>증권</mark>, '24시간 실시간 국제 금 시세' 단독 제공",
          "link": "http://www.whitepaper.co.kr/news/articleView.html?idxno=262475",
          "published_at": "6시간 전"
        },
        {
          "title": "[<mark>증권</mark>가 중계] <mark>한국</mark>투자<mark>증권</mark> '대학생 <mark>금융</mark>교육 확대', NH투자<mark>증권</mark> '코스...",
          "link": "http://www.bizwnews.com/news/articleView.html?idxno=136500",
          "published_at": "11시간 전"
        },
        {
          "title": "<mark>한국</mark><mark>금융</mark>지주 1분기 영업이익 1조1,063억원…작년 두배",
          "link": "http://www.yonhapnewstv.co.kr/news/AKR20260514164507Im6",
          "published_at": "42분 전"
        },
        {
          "title": "미래에셋 vs 한투, <mark>증권</mark>가 성장 전략 차별화..1분기 나란히 호실적",
          "link": "https://kpenews.com/View.aspx?No=4078344",
          "published_at": "1분 전"
        },
        {
          "title": "'주식 시장으로 머니무브' <mark>증권</mark>사 실적도 사상최고 행진",
          "link": "https://www.mt.co.kr/stock/2026/05/14/2026051417035339370",
          "published_at": "17분 전"
        },
        {
          "title": "미래에셋<mark>증권</mark>, 첫 분기 순익 1조 시대 열어…한투와 ‘왕좌 경쟁’ 격화",
          "link": "https://www.ceoscoredaily.com/page/view/2026051415585999064",
          "published_at": "9분 전"
        },
        {
          "title": "[<mark>증권</mark>가 NOW!] 대신·KB·신한·<mark>한국</mark>...&quot;코스피 1만500pt·연금 1위, 지원...",
          "link": "http://www.kdfnews.com/news/articleView.html?idxno=183202",
          "published_at": "7시간 전"
        },
        {
          "title": "<mark>한국</mark>투자<mark>증권</mark>, 대학생 <mark>금융</mark>교육 프로그램 확대…“2030 건전한 <mark>금융</mark> 습...",
          "link": "http://www.edaily.co.kr/news/newspath.asp?newsid=05585846645448592",
          "published_at": "23시간 전"
        }
      ]
    }
  ]
}